{
    "js": [
        "js/fixedColumns.foundation.js",
        "js/fixedColumns.foundation.min.js",
        "js/fixedColumns.foundation.min.mjs",
        "js/fixedColumns.foundation.mjs"
    ],
    "css": [
        "css/fixedColumns.foundation.css",
        "css/fixedColumns.foundation.min.css"
    ],
    "types": [
        "types/fixedColumns.foundation.d.ts"
    ],
    "src-repo": "http://github.com/DataTables/FixedColumns",
    "last-tag": "5.0.0",
    "last-sync": "9fa88b2f72611ff02a668ce1ce17aaaa8e76692d"
}